scrapy_x-1.9.dist-info/DESCRIPTION.rst
scrapy_x-1.9.dist-info/METADATA
scrapy_x-1.9.dist-info/RECORD
scrapy_x-1.9.dist-info/WHEEL
scrapy_x-1.9.dist-info/entry_points.txt
scrapy_x-1.9.dist-info/metadata.json
scrapy_x-1.9.dist-info/top_level.txt
scrapyx/__init__.py
scrapyx/routes.py
scrapyx/utils.py
scrapyx/x.py
